spotirec/__init__.py
spotirec/api.py
spotirec/conf.py
spotirec/log.py
spotirec/main.py
spotirec/oauth2.py
spotirec/recommendation.py
spotirec/spotirec.py
spotirec-1.3.1.dist-info/LICENSE
spotirec-1.3.1.dist-info/METADATA
spotirec-1.3.1.dist-info/WHEEL
spotirec-1.3.1.dist-info/entry_points.txt
spotirec-1.3.1.dist-info/top_level.txt
spotirec-1.3.1.dist-info/RECORD
