Metadata-Version: 2.1
Name: spotirec
Version: 1.3.1
Summary: A tool for creating recommended playlists for Spotify
Home-page: https://github.com/Badgie/spotirec
Author: Jonas Krogh
Author-email: jonaskhansen@gmail.com
License: GPL3
Download-URL: https://github.com/Badgie/spotirec/archive/1.3.1.tar.gz
Keywords: spotify,recommendation,music
Platform: UNKNOWN
Requires-Python: >=3.6
Requires-Dist: bottle
Requires-Dist: requests
Requires-Dist: Pillow
